{
    "primaryLinks": [
        {
            "label": "Services & Rates",
            "url": "/services",
            "icon": "arrowRight",
            "iconPosition": "right",
            "style": "secondary",
            "type": "Link",
            "altText": "services"
        },
        {
            "label": "Contact",
            "altText": "Contact",
            "url": "/contact",
            "icon": "arrowRight",
            "iconPosition": "right",
            "style": "secondary",
            "type": "Link"
        },
        {
            "label": "About",
            "altText": "About page",
            "url": "/about",
            "icon": "arrowRight",
            "iconPosition": "right",
            "style": "secondary",
            "type": "Link"
        }
    ],
    "secondaryLinks": [
        {
            "label": "Log in",
            "url": "/",
            "icon": "arrowRight",
            "iconPosition": "right",
            "style": "primary",
            "type": "Button"
        }
    ],
    "variant": "logo-left-primary-nav-centered",
    "colors": "bg-dark-fg-light",
    "type": "Header",
    "title": "The Dharmic Exchange"
}